{
	"credit": "Made with Blockbench",
	"textures": {
		"0": "minecraft:block/iron_block",
		"1": "minecraft:block/coal_block"
	},
	"elements": [
		{
			"from": [0, 0, 8],
			"to": [16, 16, 11],
			"rotation": {"angle": 0, "axis": "y", "origin": [16, 0, 0]},
			"color": 0,
			"faces": {
				"north": {"uv": [16, 0, 0, 16], "texture": "0"},
				"east": {"uv": [3, 0, 0, 16], "texture": "0"},
				"south": {"uv": [16, 0, 0, 16], "texture": "0"},
				"west": {"uv": [16, 0, 13, 16], "texture": "0"},
				"up": {"uv": [16, 0, 0, 3], "texture": "0"},
				"down": {"uv": [16, 13, 0, 16], "texture": "0"}
			}
		},
		{
			"from": [0, 0, 11],
			"to": [3, 16, 24],
			"rotation": {"angle": 0, "axis": "y", "origin": [16, 0, 0]},
			"color": 0,
			"faces": {
				"north": {"uv": [3, 0, 0, 16], "texture": "0"},
				"east": {"uv": [16, 0, 3, 16], "texture": "0"},
				"south": {"uv": [16, 0, 13, 16], "texture": "0"},
				"west": {"uv": [13, 0, 0, 16], "texture": "0"},
				"up": {"uv": [16, 3, 13, 16], "texture": "0"},
				"down": {"uv": [16, 0, 13, 13], "texture": "0"}
			}
		},
		{
			"from": [3, 0, 11],
			"to": [16, 14, 24],
			"rotation": {"angle": 0, "axis": "y", "origin": [16, 0, 0]},
			"color": 9,
			"faces": {
				"north": {"uv": [16, 0, 0, 14], "texture": "1"},
				"east": {"uv": [13, 0, 0, 14], "texture": "1"},
				"south": {"uv": [16, 0, 0, 14], "texture": "1"},
				"west": {"uv": [16, 0, 3, 14], "texture": "1"},
				"up": {"uv": [16, 0, 0, 13], "texture": "1"},
				"down": {"uv": [16, 3, 0, 16], "texture": "1"}
			}
		}
	]
}